seqdist/__init__.py
seqdist/_nbdev.py
seqdist/core.py
seqdist/ctc.py
seqdist/ctc_banded.py
seqdist/ctc_simple.py
seqdist/normalisation.py
seqdist/sparse.py
seqdist/utils.py
seqdist/cuda/ctc.cu
seqdist/cuda/ctc_banded.cu
seqdist/cuda/ctc_simple.cu
seqdist/cuda/fused_bmv.cu
seqdist/cuda/sparse.cu
seqdist/cuda/sparse_logZ.cu
seqdist/cuda/sparse_scan.cu
ont_seqdist_cuda111-0.0.4.dist-info/LICENSE
ont_seqdist_cuda111-0.0.4.dist-info/METADATA
ont_seqdist_cuda111-0.0.4.dist-info/WHEEL
ont_seqdist_cuda111-0.0.4.dist-info/entry_points.txt
ont_seqdist_cuda111-0.0.4.dist-info/top_level.txt
ont_seqdist_cuda111-0.0.4.dist-info/RECORD
